{
    "packages":{
        "zendframework\/zendframework":{
            "dev-develop":{
                "source":{
                    "reference":"c98c8ba9ca0cbaa154f84ff1cb2b20984b2343c5",
                    "time":"2012-12-04 19:33:31"
                }
            },
            "dev-master":{
                "source":{
                    "reference":"e770666d62b669432eb698fecc053ff157f1709e",
                    "time":"2012-12-04 19:33:28"
                }
            }
        },
        "zendframework\/skeleton-application":{
            "dev-master":{
                "source":{
                    "reference":"f5ffb00b0eaf811c553e374b4beb66f202f7f6c8",
                    "time":"2012-12-04 19:33:10"
                }
            }
        }
    }
}