{
    "packages":{
        "zendframework\/zendframework":{
            "dev-develop":{
                "source":{
                    "reference":"174d505d14304728eab965d261b301883cb6e5bc",
                    "time":"2012-12-04 19:31:05"
                }
            },
            "dev-master":{
                "source":{
                    "reference":"c08e75ef35a82f1d2952bbbfb8504cdcb3719511",
                    "time":"2012-12-04 19:30:57"
                }
            }
        },
        "zendframework\/skeleton-application":{
            "dev-master":{
                "source":{
                    "reference":"90bf6778ca068c42a88edd1a7a563b72da5c6a31",
                    "time":"2012-12-04 19:25:25"
                }
            }
        }
    }
}